README.md
setup.cfg
setup.py
distributions/Binomialdistribution.py
distributions/Gaussiandistribution.py
distributions/Generaldistribution.py
distributions/__init__.py
olles_Normal_and_Binomial_distributions.egg-info/PKG-INFO
olles_Normal_and_Binomial_distributions.egg-info/SOURCES.txt
olles_Normal_and_Binomial_distributions.egg-info/dependency_links.txt
olles_Normal_and_Binomial_distributions.egg-info/not-zip-safe
olles_Normal_and_Binomial_distributions.egg-info/top_level.txt