Metadata-Version: 1.0
Name: olles-Normal-and-Binomial-distributions
Version: 0.1
Summary: Normal/Gaussian and Binomial distributions
Home-page: UNKNOWN
Author: Olle Green
Author-email: olleg.green@gmail.com
License: UNKNOWN
Platform: UNKNOWN
